handelsregister/__init__.py
handelsregister/cli.py
handelsregister/client.py
handelsregister/company.py
handelsregister/exceptions.py
handelsregister/version.py
handelsregister-0.3.0.dist-info/METADATA
handelsregister-0.3.0.dist-info/WHEEL
handelsregister-0.3.0.dist-info/entry_points.txt
handelsregister-0.3.0.dist-info/top_level.txt
handelsregister-0.3.0.dist-info/RECORD
