Metadata-Version: 2.4
Name: handelsregister
Version: 0.3.0
Summary: Python SDK für den Zugriff auf die Handelsregister AI API
Home-page: https://github.com/Handelsregister-AI/handelsregister
Author: Handelsregister Team
Author-email: Handelsregister Team <info@handelsregister.ai>
License: MIT
Project-URL: Homepage, https://github.com/Handelsregister-AI/handelsregister
Project-URL: Bug Reports, https://github.com/Handelsregister-AI/handelsregister/issues
Keywords: handelsregister,api,german company data,business data
Classifier: Development Status :: 3 - Alpha
Classifier: Intended Audience :: Developers
Classifier: License :: OSI Approved :: MIT License
Classifier: Programming Language :: Python :: 3
Classifier: Programming Language :: Python :: 3.8
Classifier: Programming Language :: Python :: 3.9
Classifier: Programming Language :: Python :: 3.10
Requires-Python: >=3.7
Requires-Dist: httpx>=0.23.0
Requires-Dist: tqdm>=4.0.0
Requires-Dist: pandas>=1.0.0
Requires-Dist: openpyxl>=3.0.0
Requires-Dist: rich>=13.0.0
Dynamic: author
Dynamic: home-page
Dynamic: requires-python
